Metadata-Version: 1.1
Name: dirigible
Version: 0.2.2
Summary: Config encryption
Home-page: https://github.org/massmutual/dirigible
Author: Thom Neale
Author-email: tneale@massmutual.com
License: UNKNOWN
Keywords: dirigible
Platform: UNKNOWN
Classifier: Development Status :: 2 - Pre-Alpha
Classifier: Intended Audience :: Developers
Classifier: Natural Language :: English
Classifier: Programming Language :: Python :: 2
Classifier: Programming Language :: Python :: 2.6
Classifier: Programming Language :: Python :: 2.7
Classifier: Programming Language :: Python :: 3
Classifier: Programming Language :: Python :: 3.4
Classifier: Programming Language :: Python :: 3.5
